oneNeuron/__init__.py
oneNeuron/perceptron.py
pypi_practice_nkeyan11-0.0.2.dist-info/LICENSE
pypi_practice_nkeyan11-0.0.2.dist-info/METADATA
pypi_practice_nkeyan11-0.0.2.dist-info/WHEEL
pypi_practice_nkeyan11-0.0.2.dist-info/top_level.txt
pypi_practice_nkeyan11-0.0.2.dist-info/RECORD
