Metadata-Version: 2.1
Name: pypi-practice-nkeyan11
Version: 0.0.2
Summary: its an implimentation of Perceptron
Home-page: https://github.com/nkeyan11/pypi_practice
Author: nkeyan11
Author-email: nkeyan11@gmail.com
License: UNKNOWN
Project-URL: Bug Tracker, https://github.com/nkeyan11/pypi_practice/issues
Platform: UNKNOWN
Classifier: Programming Language :: Python :: 3
Classifier: License :: OSI Approved :: MIT License
Classifier: Operating System :: OS Independent
Requires-Python: >=3.7
License-File: LICENSE
Requires-Dist: numpy
Requires-Dist: tqdm
